jupyter_nbgallery/__init__.py
jupyter_nbgallery/commands.py
jupyter_nbgallery/nbextensions/autodownload/README.md
jupyter_nbgallery/nbextensions/autodownload/autodownload.js
jupyter_nbgallery/nbextensions/autodownload/autodownload.png
jupyter_nbgallery/nbextensions/autodownload/autodownload.yaml
jupyter_nbgallery/nbextensions/easy_buttons/README.md
jupyter_nbgallery/nbextensions/easy_buttons/easy_buttons.js
jupyter_nbgallery/nbextensions/easy_buttons/easy_buttons.png
jupyter_nbgallery/nbextensions/easy_buttons/easy_buttons.yaml
jupyter_nbgallery/nbextensions/environment/README.md
jupyter_nbgallery/nbextensions/environment/environment.js
jupyter_nbgallery/nbextensions/environment/environment.yaml
jupyter_nbgallery/nbextensions/gallery_menu/README.md
jupyter_nbgallery/nbextensions/gallery_menu/bootbox.min.js
jupyter_nbgallery/nbextensions/gallery_menu/gallery_menu.js
jupyter_nbgallery/nbextensions/gallery_menu/gallery_menu.yaml
jupyter_nbgallery/nbextensions/gallery_menu/gallery_menu_1.png
jupyter_nbgallery/nbextensions/gallery_menu/gallery_menu_2.png
jupyter_nbgallery/nbextensions/gallery_menu/preferences_menu.png
jupyter_nbgallery/nbextensions/instrumentation/README.md
jupyter_nbgallery/nbextensions/instrumentation/crypto-js-license.txt
jupyter_nbgallery/nbextensions/instrumentation/instrumentation.js
jupyter_nbgallery/nbextensions/instrumentation/instrumentation.yaml
jupyter_nbgallery/nbextensions/instrumentation/md5.js
jupyter_nbgallery-3.0.1.data/data/etc/jupyter/nbconfig/common.d/jupyter_nbgallery.json
jupyter_nbgallery-3.0.1.data/data/etc/jupyter/nbconfig/notebook.d/jupyter_nbgallery.json
jupyter_nbgallery-3.0.1.data/data/share/jupyter/nbextensions/jupyter_nbgallery/autodownload/README.md
jupyter_nbgallery-3.0.1.data/data/share/jupyter/nbextensions/jupyter_nbgallery/autodownload/autodownload.js
jupyter_nbgallery-3.0.1.data/data/share/jupyter/nbextensions/jupyter_nbgallery/autodownload/autodownload.png
jupyter_nbgallery-3.0.1.dist-info/METADATA
jupyter_nbgallery-3.0.1.dist-info/WHEEL
jupyter_nbgallery-3.0.1.dist-info/entry_points.txt
jupyter_nbgallery-3.0.1.dist-info/top_level.txt
jupyter_nbgallery-3.0.1.dist-info/RECORD
