Metadata-Version: 2.4
Name: jupyter-nbgallery
Version: 3.0.1
Summary: Jupyter extensions to add nbgallery integration
Home-page: https://github.com/nbgallery/nbgallery-extensions
Author: Ryan Festag
Author-email: rfestag@gmail.com
License: MIT
Requires-Dist: nbclassic
Requires-Dist: jupyterlab_nbgallery>=3.0.0
Dynamic: author
Dynamic: author-email
Dynamic: description
Dynamic: description-content-type
Dynamic: home-page
Dynamic: license
Dynamic: requires-dist
Dynamic: summary
